tests/__init__.py
tests/conftest.py
tests/yeying/__init__.py
tests/yeying/client/__init__.py
tests/yeying/client/test_03_uploader.py
tests/yeying/client/test_04_downloader.py
tests/yeying/client/test_05_cleanup.py
tests/yeying/client/test_06_recycle.py
tests/yeying/client/provider/__init__.py
tests/yeying/client/provider/test_01_config_provider.py
tests/yeying/client/provider/test_02_namespace_provider.py
yeying/__init__.py
yeying/version.py
yeying/api/__init__.py
yeying/api/application/__init__.py
yeying/api/application/application_pb2.py
yeying/api/application/application_pb2.pyi
yeying/api/application/application_pb2_grpc.py
yeying/api/apps/__init__.py
yeying/api/apps/zuoyepigai/__init__.py
yeying/api/apps/zuoyepigai/archive_pb2.py
yeying/api/apps/zuoyepigai/archive_pb2.pyi
yeying/api/apps/zuoyepigai/archive_pb2_grpc.py
yeying/api/apps/zuoyepigai/assignment_pb2.py
yeying/api/apps/zuoyepigai/assignment_pb2.pyi
yeying/api/apps/zuoyepigai/assignment_pb2_grpc.py
yeying/api/apps/zuoyepigai/group_pb2.py
yeying/api/apps/zuoyepigai/group_pb2.pyi
yeying/api/apps/zuoyepigai/group_pb2_grpc.py
yeying/api/apps/zuoyepigai/homework_pb2.py
yeying/api/apps/zuoyepigai/homework_pb2.pyi
yeying/api/apps/zuoyepigai/homework_pb2_grpc.py
yeying/api/apps/zuoyepigai/imagecontent_pb2.py
yeying/api/apps/zuoyepigai/imagecontent_pb2.pyi
yeying/api/apps/zuoyepigai/imagecontent_pb2_grpc.py
yeying/api/apps/zuoyepigai/message_pb2.py
yeying/api/apps/zuoyepigai/message_pb2.pyi
yeying/api/apps/zuoyepigai/message_pb2_grpc.py
yeying/api/apps/zuoyepigai/meta_pb2.py
yeying/api/apps/zuoyepigai/meta_pb2.pyi
yeying/api/apps/zuoyepigai/meta_pb2_grpc.py
yeying/api/apps/zuoyepigai/mistakes_pb2.py
yeying/api/apps/zuoyepigai/mistakes_pb2.pyi
yeying/api/apps/zuoyepigai/mistakes_pb2_grpc.py
yeying/api/apps/zuoyepigai/task_pb2.py
yeying/api/apps/zuoyepigai/task_pb2.pyi
yeying/api/apps/zuoyepigai/task_pb2_grpc.py
yeying/api/apps/zuoyepigai/tasktag_pb2.py
yeying/api/apps/zuoyepigai/tasktag_pb2.pyi
yeying_client-20250722160829.dist-info/licenses/LICENSE
yeying_client-20250722160829.dist-info/METADATA
yeying_client-20250722160829.dist-info/WHEEL
yeying_client-20250722160829.dist-info/entry_points.txt
yeying_client-20250722160829.dist-info/top_level.txt
yeying_client-20250722160829.dist-info/RECORD
