Metadata-Version: 2.4
Name: yeying_client
Version: 20250722160829
Summary: yeying python sdk
Home-page: https://github.com/yeying-community/yeying-client-python
Author: yeying-community
Author-email: yeying.community@gmail.com
Requires-Python: >=3.11
License-File: LICENSE
Requires-Dist: protobuf==6.31.1
Requires-Dist: ecdsa==0.19.0
Requires-Dist: pytest==8.4.1
Requires-Dist: cryptography>=44.0.1
Requires-Dist: grpcio==1.71.0
Requires-Dist: setuptools==80.9.0
Requires-Dist: mnemonic
Requires-Dist: web3
Requires-Dist: bip44
Requires-Dist: mara-pipelines
Requires-Dist: psycopg2-binary
Requires-Dist: bump2version
Requires-Dist: sphinx
Requires-Dist: sphinx_rtd_theme
Requires-Dist: pytest-cov
Requires-Dist: coverage
Dynamic: author
Dynamic: author-email
Dynamic: home-page
Dynamic: license-file
Dynamic: requires-dist
Dynamic: requires-python
Dynamic: summary
